{"JAPAN 1": {"number": "1", "sub_dept": "JAPAN", "offered_probabilities": [0.0, 0.0, 1.0, 1.0], "offered": ["Summer 2018", "Fall 2018", "Summer 2019", "Fall 2019", "Summer 2020", "Fall 2020", "Summer 2021", "Fall 2021", "Summer 2022", "Fall 2022", "Summer 2023", "Fall 2023"], "general_education_fields": []},
"JAPAN 2": {"number": "2", "sub_dept": "JAPAN", "offered_probabilities": [1.0, 0.0, 1.0, 0.0], "offered": ["Winter 2018", "Summer 2018", "Winter 2019", "Summer 2019", "Winter 2020", "Summer 2020", "Winter 2021", "Summer 2021", "Winter 2022", "Summer 2022", "Winter 2023", "Summer 2023"], "general_education_fields": ["H"]},
"JAPAN 3": {"number": "3", "sub_dept": "JAPAN", "offered_probabilities": [0.0, 1.0, 1.0, 0.0], "offered": ["Spring 2018", "Summer 2018", "Spring 2019", "Summer 2019", "Spring 2020", "Summer 2020", "Spring 2021", "Summer 2021", "Spring 2022", "Summer 2022", "Spring 2023", "Summer 2023"], "general_education_fields": ["B", "H"]},
"JAPAN 4": {"number": "4", "sub_dept": "JAPAN", "offered_probabilities": [0.0, 0.0, 0.0, 1.0], "offered": ["Fall 2018", "Fall 2019", "Fall 2020", "Fall 2021", "Fall 2022", "Fall 2023"], "general_education_fields": ["B", "H"]},
"JAPAN 5": {"number": "5", "sub_dept": "JAPAN", "offered_probabilities": [1.0, 0.0, 0.0, 0.0], "offered": ["Winter 2018", "Winter 2019", "Winter 2020", "Winter 2021", "Winter 2022", "Winter 2023"], "general_education_fields": ["B", "H"]},
"JAPAN 6": {"number": "6", "sub_dept": "JAPAN", "offered_probabilities": [0.0, 1.0, 0.0, 0.0], "offered": ["Spring 2018", "Spring 2019", "Spring 2020", "Spring 2021", "Spring 2022", "Spring 2023"], "general_education_fields": ["B", "H"]},
"JAPAN 17": {"number": "17", "sub_dept": "JAPAN", "offered_probabilities": [0.0, 0.09, 0.0, 0.178], "offered": ["Fall 2018", "Spring 2020", "Fall 2021"], "general_education_fields": ["NWC"]},
"JAPAN 25": {"number": "25", "sub_dept": "JAPAN", "offered_probabilities": [0.037, 0.0, 0.0, 0.0], "offered": ["Winter 2019"], "general_education_fields": ["NWC", "WRT", "D"]},
"JAPAN 63": {"number": "63", "sub_dept": "JAPAN", "offered_probabilities": [0.17, 0.037, 0.0, 0.0], "offered": ["Spring 2019", "Winter 2021"], "general_education_fields": ["NWC", "D"]},
"JAPAN 70": {"number": "70", "sub_dept": "JAPAN", "offered_probabilities": [0.008, 0.0, 0.0, 0.0], "offered": ["Winter 2018"], "general_education_fields": []},
"JAPAN 73": {"number": "73", "sub_dept": "JAPAN", "offered_probabilities": [0.0, 0.17, 0.0, 0.453], "offered": ["Fall 2019", "Spring 2021", "Fall 2023"], "general_education_fields": []},
"JAPAN 80": {"number": "80", "sub_dept": "JAPAN", "offered_probabilities": [0.0, 0.0, 0.0, 0.008], "offered": ["Fall 2018"], "general_education_fields": ["WRT", "NWC", "G"]},
"JAPAN 99": {"number": "99", "sub_dept": "JAPAN", "offered_probabilities": [0.0, 0.992, 0.0, 0.0], "offered": ["Spring 2019", "Spring 2020", "Spring 2021", "Spring 2022", "Spring 2023"], "general_education_fields": []},
"JAPAN 99RA": {"number": "99RA", "sub_dept": "JAPAN", "offered_probabilities": [0.955, 0.992, 0.0, 0.0], "offered": ["Spring 2019", "Winter 2020", "Spring 2020", "Winter 2021", "Spring 2021", "Winter 2022", "Spring 2022", "Winter 2023", "Spring 2023"], "general_education_fields": []},
"JAPAN 112": {"number": "112", "sub_dept": "JAPAN", "offered_probabilities": [0.207, 0.0, 0.0, 0.315], "offered": ["Winter 2019", "Fall 2019", "Winter 2021", "Fall 2022"], "general_education_fields": ["NWC", "WRT", "G"]},
"JAPAN 115": {"number": "115", "sub_dept": "JAPAN", "offered_probabilities": [0.514, 0.17, 0.0, 0.0], "offered": ["Winter 2018", "Winter 2020", "Spring 2021", "Winter 2023"], "general_education_fields": ["NWC", "G"]},
"JAPAN 120A": {"number": "120A", "sub_dept": "JAPAN", "offered_probabilities": [0.0, 0.0, 0.0, 0.722], "offered": ["Fall 2018", "Fall 2019", "Fall 2020", "Fall 2021", "Fall 2023"], "general_education_fields": []},
"JAPAN 120B": {"number": "120B", "sub_dept": "JAPAN", "offered_probabilities": [0.584, 0.0, 0.0, 0.0], "offered": ["Winter 2018", "Winter 2019", "Winter 2020", "Winter 2021", "Winter 2022"], "general_education_fields": []},
"JAPAN 120C": {"number": "120C", "sub_dept": "JAPAN", "offered_probabilities": [0.0, 0.584, 0.0, 0.0], "offered": ["Spring 2018", "Spring 2019", "Spring 2020", "Spring 2021", "Spring 2022"], "general_education_fields": []},
"JAPAN 134G": {"number": "134G", "sub_dept": "JAPAN", "offered_probabilities": [0.037, 0.0, 0.0, 0.0], "offered": ["Winter 2019"], "general_education_fields": ["F", "NWC"]},
"JAPAN 134H": {"number": "134H", "sub_dept": "JAPAN", "offered_probabilities": [0.0, 0.0, 0.0, 0.037], "offered": ["Fall 2019"], "general_education_fields": ["F", "NWC"]},
"JAPAN 134J": {"number": "134J", "sub_dept": "JAPAN", "offered_probabilities": [0.128, 0.0, 0.0, 0.0], "offered": ["Winter 2019", "Winter 2020"], "general_education_fields": []},
"JAPAN 136": {"number": "136", "sub_dept": "JAPAN", "offered_probabilities": [0.0, 0.416, 0.0, 0.416], "offered": ["Spring 2023", "Fall 2023"], "general_education_fields": []},
"JAPAN 138": {"number": "138", "sub_dept": "JAPAN", "offered_probabilities": [0.17, 0.0, 0.0, 0.17], "offered": ["Winter 2021", "Fall 2021"], "general_education_fields": []},
"JAPAN 140": {"number": "140", "sub_dept": "JAPAN", "offered_probabilities": [0.037, 0.0, 0.0, 0.0], "offered": ["Winter 2019"], "general_education_fields": []},
"JAPAN 142": {"number": "142", "sub_dept": "JAPAN", "offered_probabilities": [0.0, 0.0, 0.0, 0.008], "offered": ["Fall 2018"], "general_education_fields": []},
"JAPAN 144": {"number": "144", "sub_dept": "JAPAN", "offered_probabilities": [0.0, 0.0, 0.0, 1.0], "offered": ["Fall 2018", "Fall 2019", "Fall 2020", "Fall 2021", "Fall 2022", "Fall 2023"], "general_education_fields": []},
"JAPAN 145": {"number": "145", "sub_dept": "JAPAN", "offered_probabilities": [1.0, 0.0, 0.0, 0.0], "offered": ["Winter 2018", "Winter 2019", "Winter 2020", "Winter 2021", "Winter 2022", "Winter 2023"], "general_education_fields": []},
"JAPAN 146": {"number": "146", "sub_dept": "JAPAN", "offered_probabilities": [0.0, 0.269, 0.0, 0.0], "offered": ["Spring 2018", "Spring 2020", "Spring 2021"], "general_education_fields": []},
"JAPAN 149": {"number": "149", "sub_dept": "JAPAN", "offered_probabilities": [0.0, 0.008, 0.0, 0.416], "offered": ["Spring 2018", "Fall 2023"], "general_education_fields": ["F", "NWC"]},
"JAPAN 150": {"number": "150", "sub_dept": "JAPAN", "offered_probabilities": [0.278, 0.09, 0.0, 0.17], "offered": ["Spring 2020", "Fall 2021", "Winter 2022"], "general_education_fields": []},
"JAPAN 153": {"number": "153", "sub_dept": "JAPAN", "offered_probabilities": [0.416, 0.0, 0.0, 0.0], "offered": ["Winter 2023"], "general_education_fields": []},
"JAPAN 156": {"number": "156", "sub_dept": "JAPAN", "offered_probabilities": [0.0, 0.0, 0.0, 0.278], "offered": ["Fall 2022"], "general_education_fields": []},
"JAPAN 159": {"number": "159", "sub_dept": "JAPAN", "offered_probabilities": [0.0, 0.506, 0.0, 0.261], "offered": ["Spring 2020", "Fall 2020", "Fall 2021", "Spring 2023"], "general_education_fields": ["F", "NWC", "WRT"]},
"JAPAN 160": {"number": "160", "sub_dept": "JAPAN", "offered_probabilities": [0.0, 0.17, 0.0, 0.0], "offered": ["Spring 2021"], "general_education_fields": []},
"JAPAN 161": {"number": "161", "sub_dept": "JAPAN", "offered_probabilities": [0.416, 0.278, 0.0, 0.0], "offered": ["Spring 2022", "Winter 2023"], "general_education_fields": []},
"JAPAN 162": {"number": "162", "sub_dept": "JAPAN", "offered_probabilities": [0.099, 0.278, 0.0, 0.0], "offered": ["Winter 2018", "Winter 2020", "Spring 2022"], "general_education_fields": ["E", "NWC", "WRT", "D"]},
"JAPAN 164": {"number": "164", "sub_dept": "JAPAN", "offered_probabilities": [0.0, 0.17, 0.0, 0.416], "offered": ["Spring 2021", "Fall 2023"], "general_education_fields": ["E", "NWC"]},
"JAPAN 165": {"number": "165", "sub_dept": "JAPAN", "offered_probabilities": [0.278, 0.045, 1.0, 0.0], "offered": ["Spring 2018", "Summer 2018", "Spring 2019", "Summer 2019", "Summer 2020", "Summer 2021", "Winter 2022", "Summer 2022", "Summer 2023"], "general_education_fields": ["E", "NWC", "WRT", "ETH"]},
"JAPAN 166": {"number": "166", "sub_dept": "JAPAN", "offered_probabilities": [0.037, 0.0, 0.0, 0.0], "offered": ["Winter 2019"], "general_education_fields": ["E", "WRT", "NWC"]},
"JAPAN 167A": {"number": "167A", "sub_dept": "JAPAN", "offered_probabilities": [0.369, 0.037, 0.0, 0.694], "offered": ["Spring 2019", "Winter 2020", "Winter 2022", "Fall 2022", "Fall 2023"], "general_education_fields": ["WRT"]},
"JAPAN 169": {"number": "169", "sub_dept": "JAPAN", "offered_probabilities": [0.278, 0.0, 0.0, 0.0], "offered": ["Winter 2022"], "general_education_fields": []},
"JAPAN 175B": {"number": "175B", "sub_dept": "JAPAN", "offered_probabilities": [0.0, 0.369, 0.0, 0.0], "offered": ["Spring 2020", "Spring 2022"], "general_education_fields": []},
"JAPAN 180": {"number": "180", "sub_dept": "JAPAN", "offered_probabilities": [0.0, 0.037, 0.0, 0.0], "offered": ["Spring 2019"], "general_education_fields": []},
"JAPAN 180AA": {"number": "180AA", "sub_dept": "JAPAN", "offered_probabilities": [0.0, 0.0, 0.278, 0.0], "offered": ["Summer 2022"], "general_education_fields": []},
"JAPAN 180AI": {"number": "180AI", "sub_dept": "JAPAN", "offered_probabilities": [0.0, 0.037, 0.0, 0.0], "offered": ["Spring 2019"], "general_education_fields": []},
"JAPAN 180DL": {"number": "180DL", "sub_dept": "JAPAN", "offered_probabilities": [0.278, 0.0, 0.0, 0.0], "offered": ["Winter 2022"], "general_education_fields": []},
"JAPAN 180ET": {"number": "180ET", "sub_dept": "JAPAN", "offered_probabilities": [0.0, 0.416, 0.0, 0.0], "offered": ["Spring 2023"], "general_education_fields": []},
"JAPAN 180JE": {"number": "180JE", "sub_dept": "JAPAN", "offered_probabilities": [0.0, 0.0, 0.0, 0.008], "offered": ["Fall 2018"], "general_education_fields": []},
"JAPAN 180JY": {"number": "180JY", "sub_dept": "JAPAN", "offered_probabilities": [0.0, 0.128, 0.0, 0.0], "offered": ["Spring 2019", "Spring 2020"], "general_education_fields": []},
"JAPAN 180MJ": {"number": "180MJ", "sub_dept": "JAPAN", "offered_probabilities": [0.0, 0.369, 0.0, 0.0], "offered": ["Spring 2020", "Spring 2022"], "general_education_fields": []},
"JAPAN 180SJ": {"number": "180SJ", "sub_dept": "JAPAN", "offered_probabilities": [0.0, 0.0, 0.278, 0.0], "offered": ["Summer 2022"], "general_education_fields": []},
"JAPAN 180WJ": {"number": "180WJ", "sub_dept": "JAPAN", "offered_probabilities": [0.0, 0.037, 0.0, 0.0], "offered": ["Spring 2019"], "general_education_fields": []},
"JAPAN 180WL": {"number": "180WL", "sub_dept": "JAPAN", "offered_probabilities": [0.0, 0.278, 0.0, 0.0], "offered": ["Spring 2022"], "general_education_fields": []},
"JAPAN 181": {"number": "181", "sub_dept": "JAPAN", "offered_probabilities": [0.0, 0.0, 0.0, 1.0], "offered": ["Fall 2018", "Fall 2019", "Fall 2020", "Fall 2021", "Fall 2022", "Fall 2023"], "general_education_fields": []},
"JAPAN 183": {"number": "183", "sub_dept": "JAPAN", "offered_probabilities": [1.0, 0.0, 0.0, 0.0], "offered": ["Winter 2018", "Winter 2019", "Winter 2020", "Winter 2021", "Winter 2022", "Winter 2023"], "general_education_fields": []},
"JAPAN 197": {"number": "197", "sub_dept": "JAPAN", "offered_probabilities": [0.306, 0.136, 0.0, 0.045], "offered": ["Winter 2018", "Spring 2018", "Fall 2018", "Winter 2019", "Spring 2019", "Fall 2019", "Winter 2020", "Spring 2020", "Winter 2021"], "general_education_fields": []},
"JAPAN 198": {"number": "198", "sub_dept": "JAPAN", "offered_probabilities": [1.0, 0.008, 0.584, 1.0], "offered": ["Winter 2018", "Spring 2018", "Summer 2018", "Fall 2018", "Winter 2019", "Summer 2019", "Fall 2019", "Winter 2020", "Summer 2020", "Fall 2020", "Winter 2021", "Summer 2021", "Fall 2021", "Winter 2022", "Summer 2022", "Fall 2022", "Winter 2023", "Fall 2023"], "general_education_fields": []},
"JAPAN 199": {"number": "199", "sub_dept": "JAPAN", "offered_probabilities": [1.0, 1.0, 0.584, 1.0], "offered": ["Winter 2018", "Spring 2018", "Summer 2018", "Fall 2018", "Winter 2019", "Spring 2019", "Summer 2019", "Fall 2019", "Winter 2020", "Spring 2020", "Summer 2020", "Fall 2020", "Winter 2021", "Spring 2021", "Summer 2021", "Fall 2021", "Winter 2022", "Spring 2022", "Summer 2022", "Fall 2022", "Winter 2023", "Spring 2023", "Fall 2023"], "general_education_fields": []},
"JAPAN 199RA": {"number": "199RA", "sub_dept": "JAPAN", "offered_probabilities": [1.0, 1.0, 0.0, 1.0], "offered": ["Winter 2018", "Spring 2018", "Fall 2018", "Winter 2019", "Spring 2019", "Fall 2019", "Winter 2020", "Spring 2020", "Fall 2020", "Winter 2021", "Spring 2021", "Fall 2021", "Winter 2022", "Spring 2022", "Fall 2022", "Winter 2023", "Spring 2023", "Fall 2023"], "general_education_fields": []},
"JAPAN 201": {"number": "201", "sub_dept": "JAPAN", "offered_probabilities": [1.0, 0.963, 0.0, 0.864], "offered": ["Winter 2018", "Spring 2018", "Winter 2019", "Winter 2020", "Spring 2020", "Winter 2021", "Spring 2021", "Fall 2021", "Winter 2022", "Spring 2022", "Fall 2022", "Winter 2023", "Spring 2023", "Fall 2023"], "general_education_fields": []},
"JAPAN 211": {"number": "211", "sub_dept": "JAPAN", "offered_probabilities": [0.008, 0.09, 0.0, 0.586], "offered": ["Winter 2018", "Spring 2020", "Fall 2021", "Fall 2023"], "general_education_fields": []},
"JAPAN 226": {"number": "226", "sub_dept": "JAPAN", "offered_probabilities": [0.369, 0.008, 0.0, 0.0], "offered": ["Spring 2018", "Winter 2020", "Winter 2022"], "general_education_fields": []},
"JAPAN 236": {"number": "236", "sub_dept": "JAPAN", "offered_probabilities": [0.17, 0.0, 0.0, 0.0], "offered": ["Winter 2021"], "general_education_fields": []},
"JAPAN 237": {"number": "237", "sub_dept": "JAPAN", "offered_probabilities": [0.0, 0.416, 0.0, 0.0], "offered": ["Spring 2023"], "general_education_fields": []},
"JAPAN 242": {"number": "242", "sub_dept": "JAPAN", "offered_probabilities": [0.0, 0.0, 0.0, 0.008], "offered": ["Fall 2018"], "general_education_fields": []},
"JAPAN 261": {"number": "261", "sub_dept": "JAPAN", "offered_probabilities": [0.09, 0.0, 0.0, 0.278], "offered": ["Winter 2020", "Fall 2022"], "general_education_fields": []},
"JAPAN 262": {"number": "262", "sub_dept": "JAPAN", "offered_probabilities": [0.008, 0.0, 0.0, 0.0], "offered": ["Winter 2018"], "general_education_fields": []},
"JAPAN 264": {"number": "264", "sub_dept": "JAPAN", "offered_probabilities": [0.0, 0.17, 0.0, 0.0], "offered": ["Spring 2021"], "general_education_fields": []},
"JAPAN 265": {"number": "265", "sub_dept": "JAPAN", "offered_probabilities": [0.0, 0.008, 0.0, 0.0], "offered": ["Spring 2018"], "general_education_fields": []},
"JAPAN 269": {"number": "269", "sub_dept": "JAPAN", "offered_probabilities": [0.278, 0.0, 0.0, 0.0], "offered": ["Winter 2022"], "general_education_fields": []},
"JAPAN 276": {"number": "276", "sub_dept": "JAPAN", "offered_probabilities": [0.0, 0.09, 0.0, 0.0], "offered": ["Spring 2020"], "general_education_fields": []},
"JAPAN 283": {"number": "283", "sub_dept": "JAPAN", "offered_probabilities": [0.037, 0.0, 0.0, 0.0], "offered": ["Winter 2019"], "general_education_fields": []},
"JAPAN 287J": {"number": "287J", "sub_dept": "JAPAN", "offered_probabilities": [1.0, 1.0, 0.0, 1.0], "offered": ["Winter 2018", "Spring 2018", "Fall 2018", "Winter 2019", "Spring 2019", "Fall 2019", "Winter 2020", "Spring 2020", "Fall 2020", "Winter 2021", "Spring 2021", "Fall 2021", "Winter 2022", "Spring 2022", "Fall 2022", "Winter 2023", "Spring 2023", "Fall 2023"], "general_education_fields": []},
"JAPAN 501": {"number": "501", "sub_dept": "JAPAN", "offered_probabilities": [0.306, 0.306, 0.0, 0.045], "offered": ["Winter 2018", "Spring 2018", "Fall 2018", "Winter 2019", "Spring 2019", "Fall 2019", "Winter 2020", "Spring 2020", "Winter 2021", "Spring 2021"], "general_education_fields": []},
"JAPAN 596": {"number": "596", "sub_dept": "JAPAN", "offered_probabilities": [1.0, 1.0, 1.0, 1.0], "offered": ["Winter 2018", "Spring 2018", "Summer 2018", "Fall 2018", "Winter 2019", "Spring 2019", "Summer 2019", "Fall 2019", "Winter 2020", "Spring 2020", "Summer 2020", "Fall 2020", "Winter 2021", "Spring 2021", "Summer 2021", "Fall 2021", "Winter 2022", "Spring 2022", "Summer 2022", "Fall 2022", "Winter 2023", "Spring 2023", "Summer 2023", "Fall 2023"], "general_education_fields": []},
"JAPAN 597": {"number": "597", "sub_dept": "JAPAN", "offered_probabilities": [1.0, 1.0, 0.0, 1.0], "offered": ["Winter 2018", "Spring 2018", "Fall 2018", "Winter 2019", "Spring 2019", "Fall 2019", "Winter 2020", "Spring 2020", "Fall 2020", "Winter 2021", "Spring 2021", "Fall 2021", "Winter 2022", "Spring 2022", "Fall 2022", "Winter 2023", "Spring 2023", "Fall 2023"], "general_education_fields": []},
"JAPAN 598": {"number": "598", "sub_dept": "JAPAN", "offered_probabilities": [1.0, 1.0, 1.0, 1.0], "offered": ["Winter 2018", "Spring 2018", "Summer 2018", "Fall 2018", "Winter 2019", "Spring 2019", "Summer 2019", "Fall 2019", "Winter 2020", "Spring 2020", "Summer 2020", "Fall 2020", "Winter 2021", "Spring 2021", "Summer 2021", "Fall 2021", "Winter 2022", "Spring 2022", "Summer 2022", "Fall 2022", "Winter 2023", "Spring 2023", "Summer 2023", "Fall 2023"], "general_education_fields": []},
"JAPAN 599": {"number": "599", "sub_dept": "JAPAN", "offered_probabilities": [1.0, 1.0, 0.0, 1.0], "offered": ["Winter 2018", "Spring 2018", "Fall 2018", "Winter 2019", "Spring 2019", "Fall 2019", "Winter 2020", "Spring 2020", "Fall 2020", "Winter 2021", "Spring 2021", "Fall 2021", "Winter 2022", "Spring 2022", "Fall 2022", "Winter 2023", "Spring 2023", "Fall 2023"], "general_education_fields": []}
}