{"MARINCS 100B": {"title": "Modern Practices in Marine Science", "dept": "MARSC", "sub_dept": "MARINCS", "number": "100B", "prereqs": [], "prereq_description": "Marine CS 100A", "comments": "", "units": "1-6", "description": "This modularized course will introduce students to important topics in modern marine science including treatment of data, scientific ethics, scientific writing, scientific presentations, the practice of interdisciplinary research, and the campus' marine science research portfolio.", "recommended_prep": "", "professor": "STAFF", "college": "CCS", "offered": [], "majors_required_for": [], "majors_optional_for": [], "general_education_fields": []},
"MARINCS 102": {"title": "Biological Oceanography", "dept": "MARSC", "sub_dept": "MARINCS", "number": "102", "prereqs": [], "prereq_description": "Marine CS 100A", "comments": "", "units": "1-6", "description": "Current concepts in biological oceanography focusing on the coupling of biotic processes to ocean physics, chemistry and sedimentation. Emphasis on areas of active research with critical evaluation of current and seminal literature.", "recommended_prep": "", "professor": "STAFF", "college": "CCS", "offered": [], "majors_required_for": [], "majors_optional_for": [], "general_education_fields": []},
"MARINCS 160AAZZ": {"title": "Marine Science Seminar", "dept": "MARSC", "sub_dept": "MARINCS", "number": "160AAZZ", "prereqs": [], "prereq_description": "Designed for majors. Non-majors require consent of the instructor to finalize enrollment.", "comments": "", "units": "1-6", "description": "Research seminar in marine science.", "recommended_prep": "", "professor": "STAFF", "college": "CCS", "offered": [], "majors_required_for": [], "majors_optional_for": [], "general_education_fields": []}
}