{"ART 1A": {"number": "1A", "sub_dept": "ART", "offered_probabilities": [1.0, 1.0, 1.0, 1.0], "offered": ["Winter 2018", "Spring 2018", "Summer 2018", "Fall 2018", "Winter 2019", "Spring 2019", "Summer 2019", "Fall 2019", "Winter 2020", "Spring 2020", "Summer 2020", "Fall 2020", "Winter 2021", "Spring 2021", "Summer 2021", "Fall 2021", "Winter 2022", "Spring 2022", "Summer 2022", "Fall 2022", "Winter 2023", "Spring 2023", "Summer 2023", "Fall 2023"], "general_education_fields": ["F", "WRT"]},
"ART 1C": {"number": "1C", "sub_dept": "ART", "offered_probabilities": [0.0, 1.0, 0.0, 1.0], "offered": ["Spring 2018", "Fall 2018", "Spring 2019", "Fall 2019", "Spring 2020", "Fall 2020", "Spring 2021", "Fall 2021", "Spring 2022", "Fall 2022", "Spring 2023", "Fall 2023"], "general_education_fields": []},
"ART 7A": {"number": "7A", "sub_dept": "ART", "offered_probabilities": [0.0, 1.0, 0.416, 0.0], "offered": ["Spring 2018", "Spring 2019", "Spring 2020", "Spring 2021", "Spring 2022", "Spring 2023", "Summer 2023"], "general_education_fields": ["F"]},
"ART 7B": {"number": "7B", "sub_dept": "ART", "offered_probabilities": [0.0, 0.0, 0.864, 1.0], "offered": ["Fall 2018", "Fall 2019", "Fall 2020", "Summer 2021", "Fall 2021", "Summer 2022", "Fall 2022", "Summer 2023", "Fall 2023"], "general_education_fields": []},
"ART 7C": {"number": "7C", "sub_dept": "ART", "offered_probabilities": [1.0, 0.0, 0.0, 0.0], "offered": ["Winter 2018", "Winter 2019", "Winter 2020", "Winter 2021", "Winter 2022", "Winter 2023"], "general_education_fields": []},
"ART 7D": {"number": "7D", "sub_dept": "ART", "offered_probabilities": [1.0, 0.0, 0.0, 0.0], "offered": ["Winter 2018", "Winter 2019", "Winter 2020", "Winter 2021", "Winter 2022", "Winter 2023"], "general_education_fields": []},
"ART 10": {"number": "10", "sub_dept": "ART", "offered_probabilities": [1.0, 0.722, 1.0, 1.0], "offered": ["Winter 2018", "Spring 2018", "Summer 2018", "Fall 2018", "Winter 2019", "Spring 2019", "Summer 2019", "Fall 2019", "Winter 2020", "Spring 2020", "Summer 2020", "Fall 2020", "Winter 2021", "Spring 2021", "Summer 2021", "Fall 2021", "Winter 2022", "Summer 2022", "Fall 2022", "Winter 2023", "Spring 2023", "Summer 2023", "Fall 2023"], "general_education_fields": []},
"ART 12": {"number": "12", "sub_dept": "ART", "offered_probabilities": [0.416, 1.0, 0.0, 1.0], "offered": ["Spring 2018", "Fall 2018", "Spring 2019", "Fall 2019", "Spring 2020", "Fall 2020", "Spring 2021", "Fall 2021", "Spring 2022", "Fall 2022", "Winter 2023", "Spring 2023", "Fall 2023"], "general_education_fields": []},
"ART 14": {"number": "14", "sub_dept": "ART", "offered_probabilities": [1.0, 1.0, 0.0, 1.0], "offered": ["Winter 2018", "Spring 2018", "Fall 2018", "Winter 2019", "Spring 2019", "Fall 2019", "Winter 2020", "Spring 2020", "Fall 2020", "Winter 2021", "Spring 2021", "Fall 2021", "Winter 2022", "Spring 2022", "Fall 2022", "Winter 2023", "Spring 2023", "Fall 2023"], "general_education_fields": []},
"ART 18": {"number": "18", "sub_dept": "ART", "offered_probabilities": [1.0, 0.0, 1.0, 1.0], "offered": ["Winter 2018", "Summer 2018", "Fall 2018", "Winter 2019", "Summer 2019", "Fall 2019", "Winter 2020", "Summer 2020", "Fall 2020", "Winter 2021", "Summer 2021", "Fall 2021", "Winter 2022", "Summer 2022", "Fall 2022", "Winter 2023", "Summer 2023", "Fall 2023"], "general_education_fields": []},
"ART 19": {"number": "19", "sub_dept": "ART", "offered_probabilities": [0.584, 0.0, 0.0, 1.0], "offered": ["Winter 2018", "Fall 2018", "Winter 2019", "Fall 2019", "Winter 2020", "Fall 2020", "Winter 2021", "Fall 2021", "Winter 2022", "Fall 2022", "Fall 2023"], "general_education_fields": []},
"ART 22": {"number": "22", "sub_dept": "ART", "offered_probabilities": [1.0, 1.0, 0.0, 1.0], "offered": ["Winter 2018", "Spring 2018", "Fall 2018", "Winter 2019", "Spring 2019", "Fall 2019", "Winter 2020", "Spring 2020", "Fall 2020", "Winter 2021", "Spring 2021", "Fall 2021", "Winter 2022", "Spring 2022", "Fall 2022", "Winter 2023", "Spring 2023", "Fall 2023"], "general_education_fields": []},
"ART 32": {"number": "32", "sub_dept": "ART", "offered_probabilities": [0.0, 0.0, 0.0, 1.0], "offered": ["Fall 2018", "Fall 2019", "Fall 2020", "Fall 2021", "Fall 2022", "Fall 2023"], "general_education_fields": []},
"ART 100": {"number": "100", "sub_dept": "ART", "offered_probabilities": [1.0, 1.0, 1.0, 1.0], "offered": ["Winter 2018", "Spring 2018", "Summer 2018", "Fall 2018", "Winter 2019", "Spring 2019", "Summer 2019", "Fall 2019", "Winter 2020", "Spring 2020", "Summer 2020", "Fall 2020", "Winter 2021", "Spring 2021", "Summer 2021", "Fall 2021", "Winter 2022", "Spring 2022", "Summer 2022", "Fall 2022", "Winter 2023", "Spring 2023", "Summer 2023", "Fall 2023"], "general_education_fields": []},
"ART 101": {"number": "101", "sub_dept": "ART", "offered_probabilities": [0.992, 1.0, 0.0, 0.872], "offered": ["Spring 2018", "Fall 2018", "Winter 2019", "Spring 2019", "Winter 2020", "Spring 2020", "Winter 2021", "Spring 2021", "Fall 2021", "Winter 2022", "Spring 2022", "Fall 2022", "Winter 2023", "Spring 2023", "Fall 2023"], "general_education_fields": []},
"ART 102MM": {"number": "102MM", "sub_dept": "ART", "offered_probabilities": [0.0, 0.0, 0.0, 0.136], "offered": ["Fall 2018", "Fall 2019", "Fall 2020"], "general_education_fields": []},
"ART 105KY": {"number": "105KY", "sub_dept": "ART", "offered_probabilities": [0.136, 0.0, 0.0, 0.0], "offered": ["Winter 2018", "Winter 2019", "Winter 2020"], "general_education_fields": []},
"ART 105PP": {"number": "105PP", "sub_dept": "ART", "offered_probabilities": [0.864, 0.0, 0.0, 1.0], "offered": ["Fall 2018", "Fall 2019", "Fall 2020", "Winter 2021", "Fall 2021", "Winter 2022", "Fall 2022", "Winter 2023", "Fall 2023"], "general_education_fields": []},
"ART 105TD": {"number": "105TD", "sub_dept": "ART", "offered_probabilities": [0.136, 0.694, 0.0, 0.261], "offered": ["Winter 2018", "Winter 2019", "Winter 2020", "Fall 2020", "Fall 2021", "Spring 2022", "Spring 2023"], "general_education_fields": []},
"ART 106W": {"number": "106W", "sub_dept": "ART", "offered_probabilities": [0.136, 0.0, 0.0, 0.0], "offered": ["Winter 2018", "Winter 2019", "Winter 2020"], "general_education_fields": ["F"]},
"ART 106IV": {"number": "106IV", "sub_dept": "ART", "offered_probabilities": [0.0, 0.008, 0.0, 0.008], "offered": ["Spring 2018", "Fall 2018"], "general_education_fields": []},
"ART 106PP": {"number": "106PP", "sub_dept": "ART", "offered_probabilities": [0.0, 0.298, 0.0, 0.0], "offered": ["Spring 2019", "Spring 2020", "Spring 2021"], "general_education_fields": []},
"ART 110": {"number": "110", "sub_dept": "ART", "offered_probabilities": [0.298, 0.414, 0.0, 0.323], "offered": ["Spring 2018", "Fall 2018", "Winter 2019", "Spring 2019", "Fall 2019", "Winter 2020", "Spring 2020", "Winter 2021", "Spring 2022", "Fall 2022"], "general_education_fields": []},
"ART 111PP": {"number": "111PP", "sub_dept": "ART", "offered_probabilities": [0.278, 0.278, 0.0, 0.0], "offered": ["Winter 2022", "Spring 2022"], "general_education_fields": []},
"ART 112": {"number": "112", "sub_dept": "ART", "offered_probabilities": [0.045, 0.416, 0.0, 0.0], "offered": ["Winter 2018", "Winter 2019", "Spring 2023"], "general_education_fields": []},
"ART 113": {"number": "113", "sub_dept": "ART", "offered_probabilities": [0.0, 1.0, 0.0, 0.0], "offered": ["Spring 2018", "Spring 2019", "Spring 2020", "Spring 2021", "Spring 2022", "Spring 2023"], "general_education_fields": []},
"ART 117": {"number": "117", "sub_dept": "ART", "offered_probabilities": [1.0, 1.0, 1.0, 1.0], "offered": ["Winter 2018", "Spring 2018", "Summer 2018", "Fall 2018", "Winter 2019", "Spring 2019", "Summer 2019", "Fall 2019", "Winter 2020", "Spring 2020", "Summer 2020", "Fall 2020", "Winter 2021", "Spring 2021", "Summer 2021", "Fall 2021", "Winter 2022", "Spring 2022", "Summer 2022", "Fall 2022", "Winter 2023", "Spring 2023", "Summer 2023", "Fall 2023"], "general_education_fields": []},
"ART 118": {"number": "118", "sub_dept": "ART", "offered_probabilities": [0.0, 1.0, 0.0, 0.0], "offered": ["Spring 2018", "Spring 2019", "Spring 2020", "Spring 2021", "Spring 2022", "Spring 2023"], "general_education_fields": []},
"ART 120EF": {"number": "120EF", "sub_dept": "ART", "offered_probabilities": [0.09, 0.128, 0.0, 0.0], "offered": ["Spring 2019", "Winter 2020", "Spring 2020"], "general_education_fields": []},
"ART 120EL": {"number": "120EL", "sub_dept": "ART", "offered_probabilities": [0.045, 0.0, 0.0, 0.0], "offered": ["Winter 2018", "Winter 2019"], "general_education_fields": []},
"ART 120NP": {"number": "120NP", "sub_dept": "ART", "offered_probabilities": [0.416, 0.286, 0.0, 0.0], "offered": ["Spring 2018", "Spring 2022", "Winter 2023"], "general_education_fields": []},
"ART 120PP": {"number": "120PP", "sub_dept": "ART", "offered_probabilities": [0.0, 0.17, 0.0, 0.0], "offered": ["Spring 2021"], "general_education_fields": []},
"ART 122CC": {"number": "122CC", "sub_dept": "ART", "offered_probabilities": [0.0, 0.136, 0.0, 0.0], "offered": ["Spring 2018", "Spring 2019", "Spring 2020"], "general_education_fields": []},
"ART 122CD": {"number": "122CD", "sub_dept": "ART", "offered_probabilities": [0.0, 0.0, 0.09, 0.09], "offered": ["Summer 2020", "Fall 2020"], "general_education_fields": []},
"ART 122PC": {"number": "122PC", "sub_dept": "ART", "offered_probabilities": [0.416, 0.677, 0.0, 0.457], "offered": ["Fall 2018", "Spring 2020", "Spring 2021", "Fall 2021", "Fall 2022", "Winter 2023", "Spring 2023"], "general_education_fields": []},
"ART 123": {"number": "123", "sub_dept": "ART", "offered_probabilities": [0.0, 0.136, 0.0, 0.09], "offered": ["Spring 2018", "Spring 2019", "Spring 2020", "Fall 2020"], "general_education_fields": []},
"ART 124": {"number": "124", "sub_dept": "ART", "offered_probabilities": [0.278, 0.0, 0.0, 0.0], "offered": ["Winter 2022"], "general_education_fields": []},
"ART 125": {"number": "125", "sub_dept": "ART", "offered_probabilities": [0.0, 0.0, 0.136, 0.0], "offered": ["Summer 2018", "Summer 2019", "Summer 2020"], "general_education_fields": ["F"]},
"ART 126": {"number": "126", "sub_dept": "ART", "offered_probabilities": [0.0, 0.278, 0.864, 0.414], "offered": ["Fall 2018", "Fall 2019", "Fall 2020", "Summer 2021", "Spring 2022", "Summer 2022", "Fall 2022", "Summer 2023"], "general_education_fields": []},
"ART 130": {"number": "130", "sub_dept": "ART", "offered_probabilities": [0.992, 0.722, 1.0, 0.586], "offered": ["Spring 2018", "Summer 2018", "Winter 2019", "Spring 2019", "Summer 2019", "Winter 2020", "Spring 2020", "Summer 2020", "Winter 2021", "Spring 2021", "Summer 2021", "Fall 2021", "Winter 2022", "Summer 2022", "Winter 2023", "Spring 2023", "Summer 2023", "Fall 2023"], "general_education_fields": []},
"ART 132": {"number": "132", "sub_dept": "ART", "offered_probabilities": [1.0, 0.0, 0.0, 0.278], "offered": ["Winter 2018", "Winter 2019", "Winter 2020", "Winter 2021", "Winter 2022", "Fall 2022", "Winter 2023"], "general_education_fields": []},
"ART 133M": {"number": "133M", "sub_dept": "ART", "offered_probabilities": [0.694, 0.0, 0.0, 0.0], "offered": ["Winter 2022", "Winter 2023"], "general_education_fields": []},
"ART 134": {"number": "134", "sub_dept": "ART", "offered_probabilities": [0.008, 0.486, 0.0, 0.0], "offered": ["Winter 2018", "Spring 2019", "Spring 2021", "Spring 2022"], "general_education_fields": []},
"ART 136": {"number": "136", "sub_dept": "ART", "offered_probabilities": [0.0, 0.0, 0.0, 1.0], "offered": ["Fall 2018", "Fall 2019", "Fall 2020", "Fall 2021", "Fall 2022", "Fall 2023"], "general_education_fields": []},
"ART 137": {"number": "137", "sub_dept": "ART", "offered_probabilities": [0.0, 1.0, 0.0, 0.0], "offered": ["Spring 2018", "Spring 2019", "Spring 2020", "Spring 2021", "Spring 2022", "Spring 2023"], "general_education_fields": []},
"ART 177": {"number": "177", "sub_dept": "ART", "offered_probabilities": [0.008, 0.0, 0.0, 0.0], "offered": ["Winter 2018"], "general_education_fields": []},
"ART 185AA": {"number": "185AA", "sub_dept": "ART", "offered_probabilities": [0.0, 0.0, 0.0, 0.09], "offered": ["Fall 2020"], "general_education_fields": []},
"ART 185AI": {"number": "185AI", "sub_dept": "ART", "offered_probabilities": [0.207, 0.0, 0.0, 0.0], "offered": ["Winter 2019", "Winter 2021"], "general_education_fields": []},
"ART 185BD": {"number": "185BD", "sub_dept": "ART", "offered_probabilities": [0.0, 0.17, 0.0, 0.449], "offered": ["Spring 2021", "Fall 2021", "Fall 2022"], "general_education_fields": []},
"ART 185GL": {"number": "185GL", "sub_dept": "ART", "offered_probabilities": [0.0, 0.008, 0.0, 0.0], "offered": ["Spring 2018"], "general_education_fields": []},
"ART 185LJ": {"number": "185LJ", "sub_dept": "ART", "offered_probabilities": [0.0, 0.83, 0.0, 0.0], "offered": ["Spring 2018", "Spring 2019", "Spring 2020", "Spring 2022", "Spring 2023"], "general_education_fields": []},
"ART 185PR": {"number": "185PR", "sub_dept": "ART", "offered_probabilities": [0.17, 0.0, 0.0, 0.0], "offered": ["Winter 2021"], "general_education_fields": []},
"ART 185XX": {"number": "185XX", "sub_dept": "ART", "offered_probabilities": [0.586, 0.416, 0.0, 0.0], "offered": ["Winter 2021", "Winter 2023", "Spring 2023"], "general_education_fields": []},
"ART 189A": {"number": "189A", "sub_dept": "ART", "offered_probabilities": [0.0, 0.0, 0.0, 0.864], "offered": ["Fall 2021", "Fall 2022", "Fall 2023"], "general_education_fields": []},
"ART 189B": {"number": "189B", "sub_dept": "ART", "offered_probabilities": [0.694, 0.0, 0.0, 0.0], "offered": ["Winter 2022", "Winter 2023"], "general_education_fields": []},
"ART 189C": {"number": "189C", "sub_dept": "ART", "offered_probabilities": [0.0, 0.694, 0.0, 0.0], "offered": ["Spring 2022", "Spring 2023"], "general_education_fields": []},
"ART 192ES": {"number": "192ES", "sub_dept": "ART", "offered_probabilities": [1.0, 1.0, 0.0, 1.0], "offered": ["Winter 2018", "Spring 2018", "Fall 2018", "Winter 2019", "Spring 2019", "Fall 2019", "Winter 2020", "Spring 2020", "Fall 2020", "Winter 2021", "Spring 2021", "Fall 2021", "Winter 2022", "Spring 2022", "Fall 2022", "Winter 2023", "Spring 2023", "Fall 2023"], "general_education_fields": []},
"ART 192IA": {"number": "192IA", "sub_dept": "ART", "offered_probabilities": [1.0, 1.0, 0.694, 1.0], "offered": ["Winter 2018", "Spring 2018", "Fall 2018", "Winter 2019", "Spring 2019", "Fall 2019", "Winter 2020", "Spring 2020", "Fall 2020", "Winter 2021", "Spring 2021", "Fall 2021", "Winter 2022", "Spring 2022", "Summer 2022", "Fall 2022", "Winter 2023", "Spring 2023", "Summer 2023", "Fall 2023"], "general_education_fields": []},
"ART 194": {"number": "194", "sub_dept": "ART", "offered_probabilities": [0.128, 0.037, 0.0, 0.099], "offered": ["Fall 2018", "Winter 2019", "Spring 2019", "Winter 2020", "Fall 2020"], "general_education_fields": []},
"ART 196": {"number": "196", "sub_dept": "ART", "offered_probabilities": [1.0, 1.0, 0.0, 1.0], "offered": ["Winter 2018", "Spring 2018", "Fall 2018", "Winter 2019", "Spring 2019", "Fall 2019", "Winter 2020", "Spring 2020", "Fall 2020", "Winter 2021", "Spring 2021", "Fall 2021", "Winter 2022", "Spring 2022", "Fall 2022", "Winter 2023", "Spring 2023", "Fall 2023"], "general_education_fields": []},
"ART 199": {"number": "199", "sub_dept": "ART", "offered_probabilities": [1.0, 1.0, 1.0, 1.0], "offered": ["Winter 2018", "Spring 2018", "Summer 2018", "Fall 2018", "Winter 2019", "Spring 2019", "Summer 2019", "Fall 2019", "Winter 2020", "Spring 2020", "Summer 2020", "Fall 2020", "Winter 2021", "Spring 2021", "Summer 2021", "Fall 2021", "Winter 2022", "Spring 2022", "Summer 2022", "Fall 2022", "Winter 2023", "Spring 2023", "Summer 2023", "Fall 2023"], "general_education_fields": []},
"ART 199RA": {"number": "199RA", "sub_dept": "ART", "offered_probabilities": [1.0, 1.0, 1.0, 1.0], "offered": ["Winter 2018", "Spring 2018", "Summer 2018", "Fall 2018", "Winter 2019", "Spring 2019", "Summer 2019", "Fall 2019", "Winter 2020", "Spring 2020", "Summer 2020", "Fall 2020", "Winter 2021", "Spring 2021", "Summer 2021", "Fall 2021", "Winter 2022", "Spring 2022", "Summer 2022", "Fall 2022", "Winter 2023", "Spring 2023", "Summer 2023", "Fall 2023"], "general_education_fields": []},
"ART 213": {"number": "213", "sub_dept": "ART", "offered_probabilities": [0.0, 1.0, 0.0, 0.0], "offered": ["Spring 2018", "Spring 2019", "Spring 2020", "Spring 2021", "Spring 2022", "Spring 2023"], "general_education_fields": []},
"ART 244": {"number": "244", "sub_dept": "ART", "offered_probabilities": [1.0, 0.0, 0.0, 1.0], "offered": ["Winter 2018", "Fall 2018", "Winter 2019", "Fall 2019", "Winter 2020", "Fall 2020", "Winter 2021", "Fall 2021", "Winter 2022", "Fall 2022", "Winter 2023", "Fall 2023"], "general_education_fields": []},
"ART 245": {"number": "245", "sub_dept": "ART", "offered_probabilities": [0.901, 0.992, 0.0, 0.506], "offered": ["Winter 2019", "Spring 2019", "Spring 2020", "Fall 2020", "Winter 2021", "Spring 2021", "Winter 2022", "Spring 2022", "Winter 2023", "Spring 2023", "Fall 2023"], "general_education_fields": []},
"ART 246": {"number": "246", "sub_dept": "ART", "offered_probabilities": [0.0, 0.278, 0.0, 0.099], "offered": ["Fall 2018", "Fall 2020", "Spring 2022"], "general_education_fields": []},
"ART 260": {"number": "260", "sub_dept": "ART", "offered_probabilities": [0.0, 1.0, 0.0, 0.045], "offered": ["Spring 2018", "Fall 2018", "Spring 2019", "Fall 2019", "Spring 2020", "Spring 2021", "Spring 2022", "Spring 2023"], "general_education_fields": []},
"ART 261": {"number": "261", "sub_dept": "ART", "offered_probabilities": [0.0, 1.0, 0.0, 1.0], "offered": ["Spring 2018", "Fall 2018", "Spring 2019", "Fall 2019", "Spring 2020", "Fall 2020", "Spring 2021", "Fall 2021", "Spring 2022", "Fall 2022", "Spring 2023", "Fall 2023"], "general_education_fields": []},
"ART 501": {"number": "501", "sub_dept": "ART", "offered_probabilities": [1.0, 1.0, 0.0, 1.0], "offered": ["Winter 2018", "Spring 2018", "Fall 2018", "Winter 2019", "Spring 2019", "Fall 2019", "Winter 2020", "Spring 2020", "Fall 2020", "Winter 2021", "Spring 2021", "Fall 2021", "Winter 2022", "Spring 2022", "Fall 2022", "Winter 2023", "Spring 2023", "Fall 2023"], "general_education_fields": []},
"ART 591A": {"number": "591A", "sub_dept": "ART", "offered_probabilities": [1.0, 1.0, 0.0, 1.0], "offered": ["Winter 2018", "Spring 2018", "Fall 2018", "Winter 2019", "Spring 2019", "Fall 2019", "Winter 2020", "Spring 2020", "Fall 2020", "Winter 2021", "Spring 2021", "Fall 2021", "Winter 2022", "Spring 2022", "Fall 2022", "Winter 2023", "Spring 2023", "Fall 2023"], "general_education_fields": []},
"ART 593MS": {"number": "593MS", "sub_dept": "ART", "offered_probabilities": [1.0, 1.0, 0.0, 1.0], "offered": ["Winter 2018", "Spring 2018", "Fall 2018", "Winter 2019", "Spring 2019", "Fall 2019", "Winter 2020", "Spring 2020", "Fall 2020", "Winter 2021", "Spring 2021", "Fall 2021", "Winter 2022", "Spring 2022", "Fall 2022", "Winter 2023", "Spring 2023", "Fall 2023"], "general_education_fields": []},
"ART 594": {"number": "594", "sub_dept": "ART", "offered_probabilities": [1.0, 0.416, 0.0, 0.0], "offered": ["Winter 2018", "Winter 2019", "Winter 2020", "Winter 2021", "Winter 2022", "Winter 2023", "Spring 2023"], "general_education_fields": []},
"ART 595": {"number": "595", "sub_dept": "ART", "offered_probabilities": [1.0, 1.0, 0.0, 1.0], "offered": ["Winter 2018", "Spring 2018", "Fall 2018", "Winter 2019", "Spring 2019", "Fall 2019", "Winter 2020", "Spring 2020", "Fall 2020", "Winter 2021", "Spring 2021", "Fall 2021", "Winter 2022", "Spring 2022", "Fall 2022", "Winter 2023", "Spring 2023", "Fall 2023"], "general_education_fields": []}
}